./.gitignore
./PKG-INFO
./README.md
./__init__.py
./__main__.py
./pyproject.toml
./server.py
./uv.lock
getstack_mcp-2.4.0.dist-info/METADATA
getstack_mcp-2.4.0.dist-info/WHEEL
getstack_mcp-2.4.0.dist-info/entry_points.txt
getstack_mcp-2.4.0.dist-info/RECORD
