Metadata-Version: 2.4
Name: getstack-mcp
Version: 2.4.0
Summary: MCP server for managing getstack templates from Supabase database with RAG search
Project-URL: Homepage, https://github.com/olegstefanov/get-stack
Project-URL: Repository, https://github.com/olegstefanov/get-stack.git
Project-URL: Issues, https://github.com/olegstefanov/get-stack/issues
Author-email: Oleg Stefanov <coderr.oleg@gmail.com>
License: MIT
Keywords: claude,embeddings,mcp,rag,supabase,templates
Classifier: Development Status :: 4 - Beta
Classifier: Intended Audience :: Developers
Classifier: License :: OSI Approved :: MIT License
Classifier: Programming Language :: Python :: 3
Classifier: Programming Language :: Python :: 3.10
Classifier: Programming Language :: Python :: 3.11
Classifier: Programming Language :: Python :: 3.12
Requires-Python: >=3.10
Requires-Dist: gitpython>=3.1.40
Requires-Dist: mcp>=1.0.0
Requires-Dist: requests>=2.31.0
Requires-Dist: supabase>=2.0.0
Requires-Dist: uvicorn>=0.15.0
Provides-Extra: dev
Requires-Dist: uvicorn>=0.32.1; extra == 'dev'
